reduced_RISC-V/rom.sv
module rom #(parameter WAD = 8, WD = 8)(
    input logic [WAD-1: 0] AddrIn,
    output logic [WD*4-1: 0] DOut
);

logic [WD-1: 0] RomArr [2**WAD-1: 0]; // error occurs if 2^32 is used

initial begin
    $readmemh("rom.mem", RomArr);
end;

assign DOut = {RomArr[AddrIn], RomArr[AddrIn+1], RomArr[AddrIn+2], RomArr[AddrIn+3]};

endmodule

reduced_RISC-V/pcreg.sv
module pcreg #(parameter W = 32)(
    input logic clk,
    input logic rst,
    input logic [W-1: 0] PCN,
    output logic [W-1: 0] PC
);

always_ff@(posedge clk)
    if (rst) PC <= {W{1'b0}};
    else PC <= PCN;

endmodule

reduced_RISC-V/datapath2.sv
module datapath2 #(W = 32)(
    input logic clk,
    input logic rst,
    input logic PCsrc,
    input logic [W-1:0] IMMop,
    output logic [W-1:0] instr
);

logic [W-1:0] PC;
logic [W-1:0] PCN;
logic [W-1:0] branch_pc;

assign branch_pc = PC + IMMop;

always_comb begin
    if (PCsrc) PCN = branch_pc;
    else PCN = PC + 4;
end 

pcreg P1(
    .clk(clk),
    .rst(rst),
    .PCN(PCN),

    .PC(PC)
);

rom R1(
    .AddrIn(PC),

    .DOut(instr)
);


endmodule

reduced_RISC-V/aludecode.sv
module aludecode #(W = 32)(
    input logic [W-1:0] instr,
    input logic [1:0] ALUop,
    output logic [2:0] ALUctrl
);

logic [2:0] func3;
logic func75;
logic op5;

assign func3 = instr[W-18:W-20];
assign func75 = instr[W-6];
assign op5 = instr[W-30];




always_comb
case (func3)
    3'b010: ALUctrl = 3'b101; // slt
    3'b110: ALUctrl = 3'b011; // or
    3'b111: ALUctrl = 3'b010; // and

    default: ALUctrl = 3'b000;
endcase

always_comb
case ({func3, op5, func75})
    5'b00111: ALUctrl = 3'b001;
    5'b00000: ALUctrl = 3'b000;
    5'b00001: ALUctrl = 3'b000;
    5'b00010: ALUctrl = 3'b000;
endcase

always_comb
case (ALUop)
    2'b00: ALUctrl = 3'b000;
    2'b01: ALUctrl = 3'b001;
endcase


    
endmodule

reduced_RISC-V/control.sv
module control #(parameter W = 32)(
    input logic [W-1:0] instr,
    input logic EQ,
    output logic RegWrite,
    output logic [1:0] ALUop,
    output logic ALUsrc,
    output logic [1:0] IMMsrc,
    output logic PCsrc
);

// manipulation in this part ...

logic [6:0] op7;

logic PCsrc_req1;
logic PCsrc_req2;

always_comb begin
    op7 = instr[W-26:W-32];
end

// to imm.sv
always_comb 
case (op7)
    7'b0010011: IMMsrc = 2'b00; // i-type
    7'b0000011: IMMsrc = 2'b00; 

    7'b0100011: IMMsrc = 2'b01; // s-type

    7'b1100011: IMMsrc = 2'b10; // b-type

    7'b0110111: IMMsrc = 2'b11; // u-type
    7'b0010111: IMMsrc = 2'b11;
    7'b1100111: IMMsrc = 2'b11; // j-type
    7'b1101111: IMMsrc = 2'b11;

    default: IMMsrc = 2'b00;
endcase

// to alu.sv
always_comb 
case (op7)
    7'b0110011: ALUsrc = 1'b1; // Reg
    7'b0100011: ALUsrc = 1'b1; // s-type
    7'b0010011: ALUsrc = 1'b1; // i-type
    7'b0000011: ALUsrc = 1'b1; 
    default: ALUsrc = 1'b0;
endcase

// to datapath1.sv
always_comb 
case (op7)
    7'b0100011: ALUop = 2'b00; // s-type

    7'b0000011: ALUop = 2'b00; // load

    7'b1100011: ALUop = 2'b01; // b-type

    7'b0010011: ALUop = 2'b10; // i-type

    default: ALUop = 2'b00;
endcase

// to reg32.sv
always_comb 
case (op7)
    7'b0110011: RegWrite = 1'b1; // Reg
    7'b0010011: RegWrite = 1'b1; // i-type
    7'b0000011: RegWrite = 1'b1;
    7'b0110111: RegWrite = 1'b1; // u-type
    7'b0010111: RegWrite = 1'b1;
    7'b1100111: RegWrite = 1'b1; // j-type
    7'b1101111: RegWrite = 1'b1;
    default: RegWrite = 1'b0;
endcase

// to datapath2.sv
always_comb 
case (op7)
    7'b1100011: PCsrc_req1 = 1'b1; // b-type
    7'b1100111: PCsrc_req1 = 1'b1; // j-type
    7'b1101111: PCsrc_req1 = 1'b1;
    default: PCsrc_req1 = 1'b0;
endcase

always_comb 
case (EQ)
    1'b0: PCsrc_req2 = 1'b1;
    1'b1: PCsrc_req2 = 1'b0;
    default: PCsrc_req2 = 1'b0;
endcase

always_comb begin
    PCsrc = PCsrc_req1 && PCsrc_req2;
end

endmodule

reduced_RISC-V/imm.sv
module imm #(parameter W = 32)(
    input logic [1:0] IMMsrc,
    input logic [W-1:0] instr,
    output logic [W-1:0] out
);

logic sign; // for 2's complement

assign sign = instr[W-1]; // not required by extend (U / J type)

always_comb case(IMMsrc)
    2'b00: out = {{20{sign}}, instr[W-1:W-12]}; // I-type
    2'b01: out = {{20{sign}}, instr[W-1:W-7], instr[W-21:W-25]}; // S-type
    2'b10: out = {{19{sign}}, instr[W-1], instr[W-25], instr[W-2:W-7], instr[W-21:W-24], 1'b0}; //B-type
    2'b11: out = {instr[W-1:W-20], 12'b0}; // U-type, J-type
    default: out = {{20{sign}}, instr[W-1:W-12]}; // I-type
endcase

endmodule

reduced_RISC-V/alu.sv
module alu #(parameter W = 32)(
    input logic [2: 0] ALUctrl,
    input logic [W-1: 0] N1,
    input logic [W-1: 0] N2,
    output logic [W-1: 0] out,
    output logic EQ
);

always_comb
    case (ALUctrl)
        3'b000: out = N1 + N2; // add
        3'b001: out = N1 - N2; // sub
        3'b010: out = N1 & N2; // and
        3'b011: out = N1 | N2; // or
        3'b101: out = N1 < N2 ? 32'b1 : 32'b0; // set less than, slt

        default out = N1 + N2;
    endcase

always_comb begin
    if (out == 0) EQ = 1;
    else EQ = 0;
end

endmodule

reduced_RISC-V/reg32.sv
module reg32 #(parameter WAD = 5, WD = 32, R0 = 10)( // A0 = reg[10] or reg 01010
    input logic clk,
    input logic RegWrite,
    input logic [WAD-1:0] AdIn,
    input logic [WAD-1:0] AdOut1,
    input logic [WAD-1:0] AdOut2,
    output logic [WD-1:0] DIn,
    output logic [WD-1:0] DOut1,
    output logic [WD-1:0] DOut2,
    output logic [WD-1:0] A0
);

logic [WD-1: 0] examine1;
logic [WD-1: 0] RomArr [2**WAD-1: 0];

always_ff@(posedge clk)
    if (RegWrite) RomArr[AdIn] <= DIn;

assign RomArr[0] = 32'b0;

assign DOut1 = RomArr[AdOut1];
assign DOut2 = RomArr[AdOut2];

assign A0 = RomArr[R0];
assign examine1 = RomArr[AdIn];

endmodule

/* 
x0  	zero	Always zero	
x1      ra	    Return address	
x2	    sp	    Stack pointer
x3	    gp	    Global pointer	
x4	    tp	    Thread pointer	
x5	    t0	    Temporary / alternate return address
x6–7	t1–2	Temporaries
x8	    s0/fp	Saved register / frame pointer
x9	    s1	    Saved register
x10–11	a0–1	Function arguments / return values
x12–17	a2–7	Function arguments
x18–27	s2–11	Saved registers
x28–31	t3–6	Temporaries

32 floating-point extension registers

f0–7	ft0–7	Floating-point temporaries
f8–9	fs0–1	Floating-point saved registers
f10–11	fa0–1	Floating-point arguments/return values
f12–17	fa2–7	Floating-point arguments
f18–27	fs2–11	Floating-point saved registers
f28–31	ft8–11	Floating-point temporaries
*/

reduced_RISC-V/datapath1.sv
module datapath1 #(parameter WAD = 5, WD = 32)(
    input logic clk,

    input logic [WAD-1:0] AdIn,
    input logic [WAD-1:0] AdOut1,
    input logic [WAD-1:0] AdOut2,
    input logic [WD-1:0] instr,

    input logic ALUsrc,
    input logic [2:0] ALUctrl,
    input logic RegWrite,
    input logic [1:0] IMMsrc,

    output logic [WD-1:0] A0,
    output logic EQ,
    output logic [WD-1:0] IMM
);

logic [WD-1:0] DOut1;
logic [WD-1:0] DOut2;
logic [WD-1:0] N2;
logic [WD-1:0] DIn;

always_comb begin
    if (ALUsrc) N2 = IMM;
    else N2 = DOut2;
end

reg32 R1(
    .AdIn(AdIn),
    .AdOut1(AdOut1),
    .AdOut2(AdOut2),
    .DIn(DIn),
    .RegWrite(RegWrite),
    .clk(clk),

    .DOut1(DOut1),
    .DOut2(DOut2),
    .A0(A0)
);

alu A1(
    .ALUctrl(ALUctrl),
    .N1(DOut1),
    .N2(N2),

    .EQ(EQ),
    .out(DIn)
);

imm I1(
    .IMMsrc(IMMsrc),
    .instr(instr),
    .out(IMM)
);

endmodule

reduced_RISC-V/main.sv
module main #(WA = 5, WD = 32)(
    input logic clk,
    input logic rst,
    output logic [WD-1:0] A0
);

logic [WD-1:0] instr;
logic [WD-1:0] IMMop;

logic [WA-1:0] AdIn;
logic [WA-1:0] AdOut1;
logic [WA-1:0] AdOut2;

logic ALUsrc;
logic [1:0] ALUop;
logic [2:0] ALUctrl;
logic RegWrite;
logic [1:0] IMMsrc;
logic PCsrc;

logic EQ;

assign AdIn = instr[WD-21:WD-25];
assign AdOut1 = instr[WD-13:WD-17];
assign AdOut2 = instr[WD-8:WD-12];

datapath1 D1(
    .clk(clk),

    .instr(instr),

    .AdIn(AdIn),
    .AdOut1(AdOut1),
    .AdOut2(AdOut2),

    .ALUsrc(ALUsrc),
    .ALUctrl(ALUctrl),
    .RegWrite(RegWrite),
    .IMMsrc(IMMsrc),

    .IMM(IMMop),
    .EQ(EQ),
    .A0(A0)
);

control C1(
    .instr(instr),
    .EQ(EQ),

    .RegWrite(RegWrite),
    .ALUop(ALUop),
    .ALUsrc(ALUsrc),
    .IMMsrc(IMMsrc),
    .PCsrc(PCsrc)
);

aludecode A11(
    .instr(instr),
    .ALUop(ALUop),

    .ALUctrl(ALUctrl)
);

datapath2 D2(
    .clk(clk),
    .rst(rst),
    .PCsrc(PCsrc),
    .IMMop(IMMop),

    .instr(instr)
);

endmodule

reduced_RISC-V/main.vcd
$version Generated by VerilatedVcd $end
$timescale 1ps $end
 $scope module TOP $end
  $var wire 1 _ clk $end
  $var wire 1 ` rst $end
  $var wire 32 a A0 [31:0] $end
  $scope module main $end
   $var wire 32 b WA [31:0] $end
   $var wire 32 c WD [31:0] $end
   $var wire 1 _ clk $end
   $var wire 1 ` rst $end
   $var wire 32 a A0 [31:0] $end
   $var wire 32 # instr [31:0] $end
   $var wire 32 $ IMMop [31:0] $end
   $var wire 5 % AdIn [4:0] $end
   $var wire 5 & AdOut1 [4:0] $end
   $var wire 5 ' AdOut2 [4:0] $end
   $var wire 1 ( ALUsrc $end
   $var wire 2 ) ALUop [1:0] $end
   $var wire 3 * ALUctrl [2:0] $end
   $var wire 1 + RegWrite $end
   $var wire 2 , IMMsrc [1:0] $end
   $var wire 1 - PCsrc $end
   $var wire 1 . EQ $end
   $scope module A11 $end
    $var wire 32 c W [31:0] $end
    $var wire 32 # instr [31:0] $end
    $var wire 2 ) ALUop [1:0] $end
    $var wire 3 * ALUctrl [2:0] $end
    $var wire 3 / func3 [2:0] $end
    $var wire 1 0 func75 $end
    $var wire 1 1 op5 $end
   $upscope $end
   $scope module C1 $end
    $var wire 32 c W [31:0] $end
    $var wire 32 # instr [31:0] $end
    $var wire 1 . EQ $end
    $var wire 1 + RegWrite $end
    $var wire 2 ) ALUop [1:0] $end
    $var wire 1 ( ALUsrc $end
    $var wire 2 , IMMsrc [1:0] $end
    $var wire 1 - PCsrc $end
    $var wire 7 2 op7 [6:0] $end
    $var wire 1 3 PCsrc_req1 $end
    $var wire 1 4 PCsrc_req2 $end
   $upscope $end
   $scope module D1 $end
    $var wire 32 b WAD [31:0] $end
    $var wire 32 c WD [31:0] $end
    $var wire 1 _ clk $end
    $var wire 5 % AdIn [4:0] $end
    $var wire 5 & AdOut1 [4:0] $end
    $var wire 5 ' AdOut2 [4:0] $end
    $var wire 32 # instr [31:0] $end
    $var wire 1 ( ALUsrc $end
    $var wire 3 * ALUctrl [2:0] $end
    $var wire 1 + RegWrite $end
    $var wire 2 , IMMsrc [1:0] $end
    $var wire 32 a A0 [31:0] $end
    $var wire 1 . EQ $end
    $var wire 32 $ IMM [31:0] $end
    $var wire 32 5 DOut1 [31:0] $end
    $var wire 32 6 DOut2 [31:0] $end
    $var wire 32 7 N2 [31:0] $end
    $var wire 32 8 DIn [31:0] $end
    $scope module A1 $end
     $var wire 32 c W [31:0] $end
     $var wire 3 * ALUctrl [2:0] $end
     $var wire 32 5 N1 [31:0] $end
     $var wire 32 7 N2 [31:0] $end
     $var wire 32 8 out [31:0] $end
     $var wire 1 . EQ $end
    $upscope $end
    $scope module I1 $end
     $var wire 32 c W [31:0] $end
     $var wire 2 , IMMsrc [1:0] $end
     $var wire 32 # instr [31:0] $end
     $var wire 32 $ out [31:0] $end
     $var wire 1 9 sign $end
    $upscope $end
    $scope module R1 $end
     $var wire 32 b WAD [31:0] $end
     $var wire 32 c WD [31:0] $end
     $var wire 32 d R0 [31:0] $end
     $var wire 1 _ clk $end
     $var wire 1 + RegWrite $end
     $var wire 5 % AdIn [4:0] $end
     $var wire 5 & AdOut1 [4:0] $end
     $var wire 5 ' AdOut2 [4:0] $end
     $var wire 32 8 DIn [31:0] $end
     $var wire 32 5 DOut1 [31:0] $end
     $var wire 32 6 DOut2 [31:0] $end
     $var wire 32 a A0 [31:0] $end
     $var wire 32 : examine1 [31:0] $end
     $var wire 32 ; RomArr[0] [31:0] $end
     $var wire 32 < RomArr[1] [31:0] $end
     $var wire 32 = RomArr[2] [31:0] $end
     $var wire 32 > RomArr[3] [31:0] $end
     $var wire 32 ? RomArr[4] [31:0] $end
     $var wire 32 @ RomArr[5] [31:0] $end
     $var wire 32 A RomArr[6] [31:0] $end
     $var wire 32 B RomArr[7] [31:0] $end
     $var wire 32 C RomArr[8] [31:0] $end
     $var wire 32 D RomArr[9] [31:0] $end
     $var wire 32 E RomArr[10] [31:0] $end
     $var wire 32 F RomArr[11] [31:0] $end
     $var wire 32 G RomArr[12] [31:0] $end
     $var wire 32 H RomArr[13] [31:0] $end
     $var wire 32 I RomArr[14] [31:0] $end
     $var wire 32 J RomArr[15] [31:0] $end
     $var wire 32 K RomArr[16] [31:0] $end
     $var wire 32 L RomArr[17] [31:0] $end
     $var wire 32 M RomArr[18] [31:0] $end
     $var wire 32 N RomArr[19] [31:0] $end
     $var wire 32 O RomArr[20] [31:0] $end
     $var wire 32 P RomArr[21] [31:0] $end
     $var wire 32 Q RomArr[22] [31:0] $end
     $var wire 32 R RomArr[23] [31:0] $end
     $var wire 32 S RomArr[24] [31:0] $end
     $var wire 32 T RomArr[25] [31:0] $end
     $var wire 32 U RomArr[26] [31:0] $end
     $var wire 32 V RomArr[27] [31:0] $end
     $var wire 32 W RomArr[28] [31:0] $end
     $var wire 32 X RomArr[29] [31:0] $end
     $var wire 32 Y RomArr[30] [31:0] $end
     $var wire 32 Z RomArr[31] [31:0] $end
    $upscope $end
   $upscope $end
   $scope module D2 $end
    $var wire 32 c W [31:0] $end
    $var wire 1 _ clk $end
    $var wire 1 ` rst $end
    $var wire 1 - PCsrc $end
    $var wire 32 $ IMMop [31:0] $end
    $var wire 32 # instr [31:0] $end
    $var wire 32 [ PC [31:0] $end
    $var wire 32 \ PCN [31:0] $end
    $var wire 32 ] branch_pc [31:0] $end
    $scope module P1 $end
     $var wire 32 c W [31:0] $end
     $var wire 1 _ clk $end
     $var wire 1 ` rst $end
     $var wire 32 \ PCN [31:0] $end
     $var wire 32 [ PC [31:0] $end
    $upscope $end
    $scope module R1 $end
     $var wire 32 e WAD [31:0] $end
     $var wire 32 e WD [31:0] $end
     $var wire 8 ^ AddrIn [7:0] $end
     $var wire 32 # DOut [31:0] $end
    $upscope $end
   $upscope $end
  $upscope $end
 $upscope $end
$enddefinitions $end


#0
b00000000000000000000000000000000 #
b00000000000000000000000000000000 $
b00000 %
b00000 &
b00000 '
0(
b00 )
b000 *
0+
b00 ,
0-
1.
b000 /
00
01
b0000000 2
03
04
b00000000000000000000000000000000 5
b00000000000000000000000000000000 6
b00000000000000000000000000000000 7
b00000000000000000000000000000000 8
09
b00000000000000000000000000000000 :
b00000000000000000000000000000000 ;
b00000000000000000000000000000000 <
b00000000000000000000000000000000 =
b00000000000000000000000000000000 >
b00000000000000000000000000000000 ?
b00000000000000000000000000000000 @
b00000000000000000000000000000000 A
b00000000000000000000000000000000 B
b00000000000000000000000000000000 C
b00000000000000000000000000000000 D
b00000000000000000000000000000000 E
b00000000000000000000000000000000 F
b00000000000000000000000000000000 G
b00000000000000000000000000000000 H
b00000000000000000000000000000000 I
b00000000000000000000000000000000 J
b00000000000000000000000000000000 K
b00000000000000000000000000000000 L
b00000000000000000000000000000000 M
b00000000000000000000000000000000 N
b00000000000000000000000000000000 O
b00000000000000000000000000000000 P
b00000000000000000000000000000000 Q
b00000000000000000000000000000000 R
b00000000000000000000000000000000 S
b00000000000000000000000000000000 T
b00000000000000000000000000000000 U
b00000000000000000000000000000000 V
b00000000000000000000000000000000 W
b00000000000000000000000000000000 X
b00000000000000000000000000000000 Y
b00000000000000000000000000000000 Z
b00000000000000000000000000000000 [
b00000000000000000000000000000100 \
b00000000000000000000000000000000 ]
b00000000 ^
0_
0`
b00000000000000000000000000000000 a
b00000000000000000000000000000101 b
b00000000000000000000000000100000 c
b00000000000000000000000000001010 d
b00000000000000000000000000001000 e
#1
b00001111111100000000001100010011 #
b00000000000000000000000011111111 $
b00110 %
b11111 '
1(
b10 )
1+
0.
10
b0010011 2
14
b00000000000000000000000011111111 7
b00000000000000000000000011111111 8
b00000000000000000000000011111111 ]
1_
#2
0_
#3
b00000000000000000000010100010011 #
b00000000000000000000000000000000 $
b01010 %
b00000 '
1.
00
04
b00000000000000000000000000000000 7
b00000000000000000000000000000000 8
b00000000000000000000000011111111 A
b00000000000000000000000000000100 [
b00000000000000000000000000001000 \
b00000000000000000000000000000100 ]
b00000100 ^
1_
#4
0_
#5
b00000000000000000000010110010011 #
b01011 %
b00000000000000000000000000001000 [
b00000000000000000000000000001100 \
b00000000000000000000000000001000 ]
b00001000 ^
1_
#6
0_
#7
b00000000000001011000010100010011 #
b01010 %
b01011 &
b00000000000000000000000000001100 [
b00000000000000000000000000010000 \
b00000000000000000000000000001100 ]
b00001100 ^
1_
#8
0_
#9
b00000000000101011000010110010011 #
b00000000000000000000000000000001 $
b01011 %
b00001 '
0.
14
b00000000000000000000000000000001 7
b00000000000000000000000000000001 8
b00000000000000000000000000010000 [
b00000000000000000000000000010100 \
b00000000000000000000000000010001 ]
b00010000 ^
1_
#10
0_
#11
b11111110011001011001110011100011 #
b11111111111111111111111111111000 $
b11001 %
b00110 '
0(
b01 )
b001 *
0+
b10 ,
1-
b001 /
10
b1100011 2
13
b00000000000000000000000000000001 5
b00000000000000000000000011111111 6
b00000000000000000000000011111111 7
b11111111111111111111111100000010 8
19
b00000000000000000000000000000001 F
b00000000000000000000000000010100 [
b00000000000000000000000000001100 \
b00000000000000000000000000001100 ]
b00010100 ^
1_
#12
0_
#13
b00000000000001011000010100010011 #
b00000000000000000000000000000000 $
b01010 %
b00000 '
1(
b10 )
b000 *
1+
b00 ,
0-
b000 /
00
b0010011 2
03
b00000000000000000000000000000000 6
b00000000000000000000000000000000 7
b00000000000000000000000000000001 8
09
b00000000000000000000000000001100 [
b00000000000000000000000000010000 \
b00001100 ^
1_
#14
0_
#15
b00000000000101011000010110010011 #
b00000000000000000000000000000001 $
b01011 %
b00001 '
b00000000000000000000000000000001 7
b00000000000000000000000000000010 8
b00000000000000000000000000000001 :
b00000000000000000000000000000001 E
b00000000000000000000000000010000 [
b00000000000000000000000000010100 \
b00000000000000000000000000010001 ]
b00010000 ^
1_
b00000000000000000000000000000001 a
#16
0_
#17
b11111110011001011001110011100011 #
b11111111111111111111111111111000 $
b11001 %
b00110 '
0(
b01 )
b001 *
0+
b10 ,
1-
b001 /
10
b1100011 2
13
b00000000000000000000000000000010 5
b00000000000000000000000011111111 6
b00000000000000000000000011111111 7
b11111111111111111111111100000011 8
19
b00000000000000000000000000000000 :
b00000000000000000000000000000010 F
b00000000000000000000000000010100 [
b00000000000000000000000000001100 \
b00000000000000000000000000001100 ]
b00010100 ^
1_
#18
0_
#19
b00000000000001011000010100010011 #
b00000000000000000000000000000000 $
b01010 %
b00000 '
1(
b10 )
b000 *
1+
b00 ,
0-
b000 /
00
b0010011 2
03
b00000000000000000000000000000000 6
b00000000000000000000000000000000 7
b00000000000000000000000000000010 8
09
b00000000000000000000000000000001 :
b00000000000000000000000000001100 [
b00000000000000000000000000010000 \
b00001100 ^
1_
#20
0_
#21
b00000000000101011000010110010011 #
b00000000000000000000000000000001 $
b01011 %
b00001 '
b00000000000000000000000000000001 7
b00000000000000000000000000000011 8
b00000000000000000000000000000010 :
b00000000000000000000000000000010 E
b00000000000000000000000000010000 [
b00000000000000000000000000010100 \
b00000000000000000000000000010001 ]
b00010000 ^
1_
b00000000000000000000000000000010 a
#22
0_
#23
b11111110011001011001110011100011 #
b11111111111111111111111111111000 $
b11001 %
b00110 '
0(
b01 )
b001 *
0+
b10 ,
1-
b001 /
10
b1100011 2
13
b00000000000000000000000000000011 5
b00000000000000000000000011111111 6
b00000000000000000000000011111111 7
b11111111111111111111111100000100 8
19
b00000000000000000000000000000000 :
b00000000000000000000000000000011 F
b00000000000000000000000000010100 [
b00000000000000000000000000001100 \
b00000000000000000000000000001100 ]
b00010100 ^
1_
#24
0_
#25
b00000000000001011000010100010011 #
b00000000000000000000000000000000 $
b01010 %
b00000 '
1(
b10 )
b000 *
1+
b00 ,
0-
b000 /
00
b0010011 2
03
b00000000000000000000000000000000 6
b00000000000000000000000000000000 7
b00000000000000000000000000000011 8
09
b00000000000000000000000000000010 :
b00000000000000000000000000001100 [
b00000000000000000000000000010000 \
b00001100 ^
1_
#26
0_
#27
b00000000000101011000010110010011 #
b00000000000000000000000000000001 $
b01011 %
b00001 '
b00000000000000000000000000000001 7
b00000000000000000000000000000100 8
b00000000000000000000000000000011 :
b00000000000000000000000000000011 E
b00000000000000000000000000010000 [
b00000000000000000000000000010100 \
b00000000000000000000000000010001 ]
b00010000 ^
1_
b00000000000000000000000000000011 a
#28
0_
#29
b11111110011001011001110011100011 #
b11111111111111111111111111111000 $
b11001 %
b00110 '
0(
b01 )
b001 *
0+
b10 ,
1-
b001 /
10
b1100011 2
13
b00000000000000000000000000000100 5
b00000000000000000000000011111111 6
b00000000000000000000000011111111 7
b11111111111111111111111100000101 8
19
b00000000000000000000000000000000 :
b00000000000000000000000000000100 F
b00000000000000000000000000010100 [
b00000000000000000000000000001100 \
b00000000000000000000000000001100 ]
b00010100 ^
1_
#30
0_
#31
b00000000000001011000010100010011 #
b00000000000000000000000000000000 $
b01010 %
b00000 '
1(
b10 )
b000 *
1+
b00 ,
0-
b000 /
00
b0010011 2
03
b00000000000000000000000000000000 6
b00000000000000000000000000000000 7
b00000000000000000000000000000100 8
09
b00000000000000000000000000000011 :
b00000000000000000000000000001100 [
b00000000000000000000000000010000 \
b00001100 ^
1_
#32
0_
#33
b00000000000101011000010110010011 #
b00000000000000000000000000000001 $
b01011 %
b00001 '
b00000000000000000000000000000001 7
b00000000000000000000000000000101 8
b00000000000000000000000000000100 :
b00000000000000000000000000000100 E
b00000000000000000000000000010000 [
b00000000000000000000000000010100 \
b00000000000000000000000000010001 ]
b00010000 ^
1_
b00000000000000000000000000000100 a
#34
0_
#35
b11111110011001011001110011100011 #
b11111111111111111111111111111000 $
b11001 %
b00110 '
0(
b01 )
b001 *
0+
b10 ,
1-
b001 /
10
b1100011 2
13
b00000000000000000000000000000101 5
b00000000000000000000000011111111 6
b00000000000000000000000011111111 7
b11111111111111111111111100000110 8
19
b00000000000000000000000000000000 :
b00000000000000000000000000000101 F
b00000000000000000000000000010100 [
b00000000000000000000000000001100 \
b00000000000000000000000000001100 ]
b00010100 ^
1_
#36
0_
#37
b00000000000001011000010100010011 #
b00000000000000000000000000000000 $
b01010 %
b00000 '
1(
b10 )
b000 *
1+
b00 ,
0-
b000 /
00
b0010011 2
03
b00000000000000000000000000000000 6
b00000000000000000000000000000000 7
b00000000000000000000000000000101 8
09
b00000000000000000000000000000100 :
b00000000000000000000000000001100 [
b00000000000000000000000000010000 \
b00001100 ^
1_
#38
0_
#39
b00000000000101011000010110010011 #
b00000000000000000000000000000001 $
b01011 %
b00001 '
b00000000000000000000000000000001 7
b00000000000000000000000000000110 8
b00000000000000000000000000000101 :
b00000000000000000000000000000101 E
b00000000000000000000000000010000 [
b00000000000000000000000000010100 \
b00000000000000000000000000010001 ]
b00010000 ^
1_
b00000000000000000000000000000101 a
#40
0_
#41
b11111110011001011001110011100011 #
b11111111111111111111111111111000 $
b11001 %
b00110 '
0(
b01 )
b001 *
0+
b10 ,
1-
b001 /
10
b1100011 2
13
b00000000000000000000000000000110 5
b00000000000000000000000011111111 6
b00000000000000000000000011111111 7
b11111111111111111111111100000111 8
19
b00000000000000000000000000000000 :
b00000000000000000000000000000110 F
b00000000000000000000000000010100 [
b00000000000000000000000000001100 \
b00000000000000000000000000001100 ]
b00010100 ^
1_
#42
0_
#43
b00000000000001011000010100010011 #
b00000000000000000000000000000000 $
b01010 %
b00000 '
1(
b10 )
b000 *
1+
b00 ,
0-
b000 /
00
b0010011 2
03
b00000000000000000000000000000000 6
b00000000000000000000000000000000 7
b00000000000000000000000000000110 8
09
b00000000000000000000000000000101 :
b00000000000000000000000000001100 [
b00000000000000000000000000010000 \
b00001100 ^
1_
#44
0_
#45
b00000000000101011000010110010011 #
b00000000000000000000000000000001 $
b01011 %
b00001 '
b00000000000000000000000000000001 7
b00000000000000000000000000000111 8
b00000000000000000000000000000110 :
b00000000000000000000000000000110 E
b00000000000000000000000000010000 [
b00000000000000000000000000010100 \
b00000000000000000000000000010001 ]
b00010000 ^
1_
b00000000000000000000000000000110 a
#46
0_
#47
b11111110011001011001110011100011 #
b11111111111111111111111111111000 $
b11001 %
b00110 '
0(
b01 )
b001 *
0+
b10 ,
1-
b001 /
10
b1100011 2
13
b00000000000000000000000000000111 5
b00000000000000000000000011111111 6
b00000000000000000000000011111111 7
b11111111111111111111111100001000 8
19
b00000000000000000000000000000000 :
b00000000000000000000000000000111 F
b00000000000000000000000000010100 [
b00000000000000000000000000001100 \
b00000000000000000000000000001100 ]
b00010100 ^
1_
#48
0_
#49
b00000000000001011000010100010011 #
b00000000000000000000000000000000 $
b01010 %
b00000 '
1(
b10 )
b000 *
1+
b00 ,
0-
b000 /
00
b0010011 2
03
b00000000000000000000000000000000 6
b00000000000000000000000000000000 7
b00000000000000000000000000000111 8
09
b00000000000000000000000000000110 :
b00000000000000000000000000001100 [
b00000000000000000000000000010000 \
b00001100 ^
1_
#50
0_
#51
b00000000000101011000010110010011 #
b00000000000000000000000000000001 $
b01011 %
b00001 '
b00000000000000000000000000000001 7
b00000000000000000000000000001000 8
b00000000000000000000000000000111 :
b00000000000000000000000000000111 E
b00000000000000000000000000010000 [
b00000000000000000000000000010100 \
b00000000000000000000000000010001 ]
b00010000 ^
1_
b00000000000000000000000000000111 a
#52
0_
#53
b11111110011001011001110011100011 #
b11111111111111111111111111111000 $
b11001 %
b00110 '
0(
b01 )
b001 *
0+
b10 ,
1-
b001 /
10
b1100011 2
13
b00000000000000000000000000001000 5
b00000000000000000000000011111111 6
b00000000000000000000000011111111 7
b11111111111111111111111100001001 8
19
b00000000000000000000000000000000 :
b00000000000000000000000000001000 F
b00000000000000000000000000010100 [
b00000000000000000000000000001100 \
b00000000000000000000000000001100 ]
b00010100 ^
1_
#54
0_
#55
b00000000000001011000010100010011 #
b00000000000000000000000000000000 $
b01010 %
b00000 '
1(
b10 )
b000 *
1+
b00 ,
0-
b000 /
00
b0010011 2
03
b00000000000000000000000000000000 6
b00000000000000000000000000000000 7
b00000000000000000000000000001000 8
09
b00000000000000000000000000000111 :
b00000000000000000000000000001100 [
b00000000000000000000000000010000 \
b00001100 ^
1_
#56
0_
#57
b00000000000101011000010110010011 #
b00000000000000000000000000000001 $
b01011 %
b00001 '
b00000000000000000000000000000001 7
b00000000000000000000000000001001 8
b00000000000000000000000000001000 :
b00000000000000000000000000001000 E
b00000000000000000000000000010000 [
b00000000000000000000000000010100 \
b00000000000000000000000000010001 ]
b00010000 ^
1_
b00000000000000000000000000001000 a
#58
0_
#59
b11111110011001011001110011100011 #
b11111111111111111111111111111000 $
b11001 %
b00110 '
0(
b01 )
b001 *
0+
b10 ,
1-
b001 /
10
b1100011 2
13
b00000000000000000000000000001001 5
b00000000000000000000000011111111 6
b00000000000000000000000011111111 7
b11111111111111111111111100001010 8
19
b00000000000000000000000000000000 :
b00000000000000000000000000001001 F
b00000000000000000000000000010100 [
b00000000000000000000000000001100 \
b00000000000000000000000000001100 ]
b00010100 ^
1_
#60
0_
#61
b00000000000001011000010100010011 #
b00000000000000000000000000000000 $
b01010 %
b00000 '
1(
b10 )
b000 *
1+
b00 ,
0-
b000 /
00
b0010011 2
03
b00000000000000000000000000000000 6
b00000000000000000000000000000000 7
b00000000000000000000000000001001 8
09
b00000000000000000000000000001000 :
b00000000000000000000000000001100 [
b00000000000000000000000000010000 \
b00001100 ^
1_
#62
0_
#63
b00000000000101011000010110010011 #
b00000000000000000000000000000001 $
b01011 %
b00001 '
b00000000000000000000000000000001 7
b00000000000000000000000000001010 8
b00000000000000000000000000001001 :
b00000000000000000000000000001001 E
b00000000000000000000000000010000 [
b00000000000000000000000000010100 \
b00000000000000000000000000010001 ]
b00010000 ^
1_
b00000000000000000000000000001001 a
#64
0_
#65
b11111110011001011001110011100011 #
b11111111111111111111111111111000 $
b11001 %
b00110 '
0(
b01 )
b001 *
0+
b10 ,
1-
b001 /
10
b1100011 2
13
b00000000000000000000000000001010 5
b00000000000000000000000011111111 6
b00000000000000000000000011111111 7
b11111111111111111111111100001011 8
19
b00000000000000000000000000000000 :
b00000000000000000000000000001010 F
b00000000000000000000000000010100 [
b00000000000000000000000000001100 \
b00000000000000000000000000001100 ]
b00010100 ^
1_
#66
0_
